zgtf/__init__.py
zgtf/zgtf.py
zgtf-0.1.2.data/scripts/gtf2bed12
zgtf-0.1.2.dist-info/LICENSE
zgtf-0.1.2.dist-info/METADATA
zgtf-0.1.2.dist-info/WHEEL
zgtf-0.1.2.dist-info/top_level.txt
zgtf-0.1.2.dist-info/RECORD
