Metadata-Version: 2.1
Name: zgtf
Version: 0.1.2
Summary: gtf conversion utility.
Home-page: UNKNOWN
Author: Foivos Gypas
Author-email: foivos.gypas@unibas.ch
License: UNKNOWN
Keywords: zgtf
Platform: UNKNOWN
Classifier: Programming Language :: Python :: 3.6
Requires-Dist: htseq (>=0.11)
